pdmdtable/__init__.py
pdmdtable/pdmdtable.py
pdmdtable-0.0.1.dist-info/LICENSE
pdmdtable-0.0.1.dist-info/METADATA
pdmdtable-0.0.1.dist-info/WHEEL
pdmdtable-0.0.1.dist-info/top_level.txt
pdmdtable-0.0.1.dist-info/RECORD
