Metadata-Version: 2.1
Name: pdmdtable
Version: 0.0.1
Summary: Tool to assemble ASCII tables compatible with Pandoc's Markdown extensions
Author-email: Nick Muggio <nick@mugg.io>
License: MIT License
Classifier: License :: OSI Approved :: MIT License
License-File: LICENSE
